fenix_pipeline/__init__.py
tests/__init__.py
fenix_pipeline_sdk-0.9.3.dist-info/LICENSE
fenix_pipeline_sdk-0.9.3.dist-info/METADATA
fenix_pipeline_sdk-0.9.3.dist-info/WHEEL
fenix_pipeline_sdk-0.9.3.dist-info/top_level.txt
fenix_pipeline_sdk-0.9.3.dist-info/RECORD
