Metadata-Version: 2.1
Name: fenix-pipeline-sdk
Version: 0.9.3
Summary: SDK for interacting with the Fenix Pipeline API
Home-page: https://github.com/fenix-blockchain/fenix-pipeline
Author: Fenix Blockchain Technology
Author-email: support@fenixblockchain.com
License: MIT License
Keywords: fenix pipeline sdk
Platform: UNKNOWN
Classifier: Development Status :: 4 - Beta
Classifier: Framework :: AsyncIO
Classifier: Intended Audience :: Developers
Classifier: Intended Audience :: Financial and Insurance Industry
Classifier: License :: OSI Approved :: MIT License
Classifier: Programming Language :: Python :: 3 :: Only
Classifier: Programming Language :: Python :: 3.7
Classifier: Topic :: Office/Business :: Financial
Requires-Python: >=3.7
Requires-Dist: websockets (>=8.0.2)
